MANIFEST.in
README.md
pyproject.toml
setup.cfg
lambdalumaapi.egg-info/PKG-INFO
lambdalumaapi.egg-info/SOURCES.txt
lambdalumaapi.egg-info/dependency_links.txt
lambdalumaapi.egg-info/entry_points.txt
lambdalumaapi.egg-info/requires.txt
lambdalumaapi.egg-info/top_level.txt
lumaapi/__init__.py
scripts/run_lumaapi.py